uinames/__init__.py
uinames/api.py
uinames/models.py
uinames/utils.py
uinames-1.0.0.dist-info/DESCRIPTION.rst
uinames-1.0.0.dist-info/METADATA
uinames-1.0.0.dist-info/RECORD
uinames-1.0.0.dist-info/WHEEL
uinames-1.0.0.dist-info/metadata.json
uinames-1.0.0.dist-info/top_level.txt
